ruamel/std/warnings/__init__.py
ruamel.std.warnings-0.3.0.dist-info/METADATA
ruamel.std.warnings-0.3.0.dist-info/WHEEL
ruamel.std.warnings-0.3.0.dist-info/entry_points.txt
ruamel.std.warnings-0.3.0.dist-info/top_level.txt
ruamel.std.warnings-0.3.0.dist-info/RECORD
