Metadata-Version: 2.1
Name: ruamel.std.warnings
Version: 0.3.0
Summary: extend warnings.warn with callee parameter
Home-page: https://sourceforge.net/p/ruamel-std-warnings/code/ci/default/tree
Author: Anthon van der Neut
Author-email: a.van.der.neut@ruamel.eu
License: Copyright Ruamel bvba 2007-2023
Keywords: pypi statistics
Classifier: Development Status :: 4 - Beta
Classifier: Intended Audience :: Developers
Classifier: License :: Other/Proprietary License
Classifier: Operating System :: OS Independent
Classifier: Programming Language :: Python
Requires-Python: >=3
